funkify/__about__.py
funkify/__init__.py
funkify/__main__.py
funkify/py.typed
funkify-0.7.0.dist-info/WHEEL
funkify-0.7.0.dist-info/METADATA
funkify-0.7.0.dist-info/RECORD
